PySide6/Qt/lib/libQt6QuickStudioApplication.so
PySide6/Qt/lib/libQt6QuickStudioApplication.so.6
PySide6/Qt/lib/libQt6QuickStudioApplication.so.6.0.0
PySide6/Qt/lib/libQt6QuickStudioComponents.so
PySide6/Qt/lib/libQt6QuickStudioComponents.so.6
PySide6/Qt/lib/libQt6QuickStudioComponents.so.6.0.0
PySide6/Qt/lib/libQt6QuickStudioDesignEffects.so
PySide6/Qt/lib/libQt6QuickStudioDesignEffects.so.6
PySide6/Qt/lib/libQt6QuickStudioDesignEffects.so.6.0.0
PySide6/Qt/lib/libQt6QuickStudioEffects.so
PySide6/Qt/lib/libQt6QuickStudioEffects.so.6
PySide6/Qt/lib/libQt6QuickStudioEffects.so.6.0.0
PySide6/Qt/lib/libQt6QuickStudioEventSimulator.so
PySide6/Qt/lib/libQt6QuickStudioEventSimulator.so.6
PySide6/Qt/lib/libQt6QuickStudioEventSimulator.so.6.0.0
PySide6/Qt/lib/libQt6QuickStudioEventSystem.so
PySide6/Qt/lib/libQt6QuickStudioEventSystem.so.6
PySide6/Qt/lib/libQt6QuickStudioEventSystem.so.6.0.0
PySide6/Qt/lib/libQt6QuickStudioLogicHelper.so
PySide6/Qt/lib/libQt6QuickStudioLogicHelper.so.6
PySide6/Qt/lib/libQt6QuickStudioLogicHelper.so.6.0.0
PySide6/Qt/lib/libQt6QuickStudioMultiText.so
PySide6/Qt/lib/libQt6QuickStudioMultiText.so.6
PySide6/Qt/lib/libQt6QuickStudioMultiText.so.6.0.0
PySide6/Qt/lib/libQt6QuickStudioUtils.so
PySide6/Qt/lib/libQt6QuickStudioUtils.so.6
PySide6/Qt/lib/libQt6QuickStudioUtils.so.6.0.0
PySide6/Qt/qml/QtQuick/Studio/Application/libquickstudioapplicationplugin.so
PySide6/Qt/qml/QtQuick/Studio/Application/plugins.qmltypes
PySide6/Qt/qml/QtQuick/Studio/Application/qmldir
PySide6/Qt/qml/QtQuick/Studio/Application/quickstudioapplicationplugin.debug
PySide6/Qt/qml/QtQuick/Studio/Components/ArcArrow.qml
PySide6/Qt/qml/QtQuick/Studio/Components/ArcItem.qml
PySide6/Qt/qml/QtQuick/Studio/Components/BorderItem.qml
PySide6/Qt/qml/QtQuick/Studio/Components/EllipseItem.qml
PySide6/Qt/qml/QtQuick/Studio/Components/FlipableItem.qml
PySide6/Qt/qml/QtQuick/Studio/Components/GroupItem.qml
PySide6/Qt/qml/QtQuick/Studio/Components/PieItem.qml
PySide6_DS-4.6.dist-info/METADATA
PySide6_DS-4.6.dist-info/WHEEL
PySide6_DS-4.6.dist-info/top_level.txt
PySide6_DS-4.6.dist-info/RECORD
